{"title": "Onsen Yousei Hakone-chan", "description": "The story follows Hakone, a hot spring spirit who descended to a spa resort on Earth. However, with her long slumber, she looks like a little girl on the outside. (\"Y\u014dsei\" in the title is a wordplay on the Japanese words for fairy and a young child.) The high school boy T\u014dya stumbles across her at a hot spring and ends up joining Hakone in retrieving her original powers.", "cover_img": "https://cdn.readdetectiveconan.com/file/mangapill/i/3280.jpg", "type": "manga", "status": "publishing", "year": "2012", "chapters": [{"name": "Chapter 0", "order": 0, "panels": ["https://cdn.readdetectiveconan.com/file/mangap/3280/10001000/1.jpg", "https://cdn.readdetectiveconan.com/file/mangap/3280/10001000/2.jpg", "https://cdn.readdetectiveconan.com/file/mangap/3280/10001000/3.jpg", "https://cdn.readdetectiveconan.com/file/mangap/3280/10001000/4.jpg", "https://cdn.readdetectiveconan.com/file/mangap/3280/10001000/5.jpg", "https://cdn.readdetectiveconan.com/file/mangap/3280/10001000/6.jpg", "https://cdn.readdetectiveconan.com/file/mangap/3280/10001000/7.jpg", "https://cdn.readdetectiveconan.com/file/mangap/3280/10001000/8.jpg", "https://cdn.readdetectiveconan.com/file/mangap/3280/10001000/9.jpg", "https://cdn.readdetectiveconan.com/file/mangap/3280/10001000/10.jpg", "https://cdn.readdetectiveconan.com/file/mangap/3280/10001000/11.jpg", "https://cdn.readdetectiveconan.com/file/mangap/3280/10001000/12.jpg", "https://cdn.readdetectiveconan.com/file/mangap/3280/10001000/13.jpg", "https://cdn.readdetectiveconan.com/file/mangap/3280/10001000/14.jpg", "https://cdn.readdetectiveconan.com/file/mangap/3280/10001000/15.jpg", "https://cdn.readdetectiveconan.com/file/mangap/3280/10001000/16.jpg", "https://cdn.readdetectiveconan.com/file/mangap/3280/10001000/17.jpg"]}, {"name": "Chapter 1", "order": 1, "panels": ["https://cdn.readdetectiveconan.com/file/mangap/3280/10002000/1.jpg", "https://cdn.readdetectiveconan.com/file/mangap/3280/10002000/2.jpg", "https://cdn.readdetectiveconan.com/file/mangap/3280/10002000/3.jpg", "https://cdn.readdetectiveconan.com/file/mangap/3280/10002000/4.jpg", "https://cdn.readdetectiveconan.com/file/mangap/3280/10002000/5.jpg", "https://cdn.readdetectiveconan.com/file/mangap/3280/10002000/6.jpg", "https://cdn.readdetectiveconan.com/file/mangap/3280/10002000/7.jpg", "https://cdn.readdetectiveconan.com/file/mangap/3280/10002000/8.jpg", "https://cdn.readdetectiveconan.com/file/mangap/3280/10002000/9.jpg", "https://cdn.readdetectiveconan.com/file/mangap/3280/10002000/10.jpg", "https://cdn.readdetectiveconan.com/file/mangap/3280/10002000/11.jpg", "https://cdn.readdetectiveconan.com/file/mangap/3280/10002000/12.jpg", "https://cdn.readdetectiveconan.com/file/mangap/3280/10002000/13.jpg", "https://cdn.readdetectiveconan.com/file/mangap/3280/10002000/14.jpg", "https://cdn.readdetectiveconan.com/file/mangap/3280/10002000/15.jpg", "https://cdn.readdetectiveconan.com/file/mangap/3280/10002000/16.jpg", "https://cdn.readdetectiveconan.com/file/mangap/3280/10002000/17.jpg"]}], "chapter_links": ["https://mangapill.com/chapters/3280-10001000/onsen-yousei-hakone-chan-chapter-1", "https://mangapill.com/chapters/3280-10002000/onsen-yousei-hakone-chan-chapter-2"]}