{"title": "Reiwa Hanamaru Gakuen", "description": "Hanamaru Academy is just like any other all girls' school, but it has one big difference: the lovely, lively ladies that make up its student body are all handsome hunks! From the cute uniforms to their pastimes, these boys live every day of their youth to the fullest. A hidden paradise of \"JK Danshi\" awaits!", "cover_img": "https://cdn.readdetectiveconan.com/file/mangapill/i/5047.jpg", "type": "manga", "status": "publishing", "year": "2019", "chapters": [{"name": "Chapter 29", "order": 29, "panels": ["https://cdn.readdetectiveconan.com/file/mangap/5047/10032000/1.jpeg", "https://cdn.readdetectiveconan.com/file/mangap/5047/10032000/2.jpeg", "https://cdn.readdetectiveconan.com/file/mangap/5047/10032000/3.jpeg", "https://cdn.readdetectiveconan.com/file/mangap/5047/10032000/4.jpeg", "https://cdn.readdetectiveconan.com/file/mangap/5047/10032000/5.jpeg", "https://cdn.readdetectiveconan.com/file/mangap/5047/10032000/6.jpeg", "https://cdn.readdetectiveconan.com/file/mangap/5047/10032000/7.jpeg", "https://cdn.readdetectiveconan.com/file/mangap/5047/10032000/8.jpeg", "https://cdn.readdetectiveconan.com/file/mangap/5047/10032000/9.jpeg", "https://cdn.readdetectiveconan.com/file/mangap/5047/10032000/10.jpeg", "https://cdn.readdetectiveconan.com/file/mangap/5047/10032000/11.jpeg", "https://cdn.readdetectiveconan.com/file/mangap/5047/10032000/12.jpeg", "https://cdn.readdetectiveconan.com/file/mangap/5047/10032000/13.jpeg", "https://cdn.readdetectiveconan.com/file/mangap/5047/10032000/14.jpeg", "https://cdn.readdetectiveconan.com/file/mangap/5047/10032000/15.jpeg", "https://cdn.readdetectiveconan.com/file/mangap/5047/10032000/16.jpeg", "https://cdn.readdetectiveconan.com/file/mangap/5047/10032000/17.jpeg", "https://cdn.readdetectiveconan.com/file/mangap/5047/10032000/18.jpeg", "https://cdn.readdetectiveconan.com/file/mangap/5047/10032000/19.jpeg", "https://cdn.readdetectiveconan.com/file/mangap/5047/10032000/20.jpeg", "https://cdn.readdetectiveconan.com/file/mangap/5047/10032000/21.jpeg", "https://cdn.readdetectiveconan.com/file/mangap/5047/10032000/22.jpeg"]}, {"name": "Chapter 27", "order": 27, "panels": ["https://cdn.readdetectiveconan.com/file/mangap/5047/10030000/1.jpeg", "https://cdn.readdetectiveconan.com/file/mangap/5047/10030000/2.jpeg", "https://cdn.readdetectiveconan.com/file/mangap/5047/10030000/3.jpeg", "https://cdn.readdetectiveconan.com/file/mangap/5047/10030000/4.jpeg", "https://cdn.readdetectiveconan.com/file/mangap/5047/10030000/5.jpeg", "https://cdn.readdetectiveconan.com/file/mangap/5047/10030000/6.jpeg", "https://cdn.readdetectiveconan.com/file/mangap/5047/10030000/7.jpeg", "https://cdn.readdetectiveconan.com/file/mangap/5047/10030000/8.jpeg", "https://cdn.readdetectiveconan.com/file/mangap/5047/10030000/9.jpeg", "https://cdn.readdetectiveconan.com/file/mangap/5047/10030000/10.jpeg", "https://cdn.readdetectiveconan.com/file/mangap/5047/10030000/11.jpeg", "https://cdn.readdetectiveconan.com/file/mangap/5047/10030000/12.jpeg", "https://cdn.readdetectiveconan.com/file/mangap/5047/10030000/13.jpeg"]}, {"name": "Chapter 25", "order": 25, "panels": ["https://cdn.readdetectiveconan.com/file/mangap/5047/10028000/1.jpeg", "https://cdn.readdetectiveconan.com/file/mangap/5047/10028000/2.jpeg", "https://cdn.readdetectiveconan.com/file/mangap/5047/10028000/3.jpeg", "https://cdn.readdetectiveconan.com/file/mangap/5047/10028000/4.jpeg", "https://cdn.readdetectiveconan.com/file/mangap/5047/10028000/5.jpeg", "https://cdn.readdetectiveconan.com/file/mangap/5047/10028000/6.jpeg", "https://cdn.readdetectiveconan.com/file/mangap/5047/10028000/7.jpeg", "https://cdn.readdetectiveconan.com/file/mangap/5047/10028000/8.jpeg", "https://cdn.readdetectiveconan.com/file/mangap/5047/10028000/9.jpeg", "https://cdn.readdetectiveconan.com/file/mangap/5047/10028000/10.jpeg", "https://cdn.readdetectiveconan.com/file/mangap/5047/10028000/11.jpeg", "https://cdn.readdetectiveconan.com/file/mangap/5047/10028000/12.jpeg", "https://cdn.readdetectiveconan.com/file/mangap/5047/10028000/13.jpeg", "https://cdn.readdetectiveconan.com/file/mangap/5047/10028000/14.jpeg"]}, {"name": "Chapter 28", "order": 28, "panels": ["https://cdn.readdetectiveconan.com/file/mangap/5047/10031000/1.jpeg", "https://cdn.readdetectiveconan.com/file/mangap/5047/10031000/2.jpeg", "https://cdn.readdetectiveconan.com/file/mangap/5047/10031000/3.jpeg", "https://cdn.readdetectiveconan.com/file/mangap/5047/10031000/4.jpeg", "https://cdn.readdetectiveconan.com/file/mangap/5047/10031000/5.jpeg", "https://cdn.readdetectiveconan.com/file/mangap/5047/10031000/6.jpeg", "https://cdn.readdetectiveconan.com/file/mangap/5047/10031000/7.jpeg", "https://cdn.readdetectiveconan.com/file/mangap/5047/10031000/8.jpeg", "https://cdn.readdetectiveconan.com/file/mangap/5047/10031000/9.jpeg", "https://cdn.readdetectiveconan.com/file/mangap/5047/10031000/10.jpeg"]}, {"name": "Chapter 24", "order": 24, "panels": ["https://cdn.readdetectiveconan.com/file/mangap/5047/10027500/1.jpeg", "https://cdn.readdetectiveconan.com/file/mangap/5047/10027500/2.jpeg", "https://cdn.readdetectiveconan.com/file/mangap/5047/10027500/3.jpeg", "https://cdn.readdetectiveconan.com/file/mangap/5047/10027500/4.jpeg", "https://cdn.readdetectiveconan.com/file/mangap/5047/10027500/5.jpeg", "https://cdn.readdetectiveconan.com/file/mangap/5047/10027500/6.jpeg", "https://cdn.readdetectiveconan.com/file/mangap/5047/10027500/7.jpeg", "https://cdn.readdetectiveconan.com/file/mangap/5047/10027500/8.jpeg", "https://cdn.readdetectiveconan.com/file/mangap/5047/10027500/9.jpeg", "https://cdn.readdetectiveconan.com/file/mangap/5047/10027500/10.jpeg"]}, {"name": "Chapter 21", "order": 21, "panels": ["https://cdn.readdetectiveconan.com/file/mangap/5047/10025000/1.jpeg", "https://cdn.readdetectiveconan.com/file/mangap/5047/10025000/2.jpeg", "https://cdn.readdetectiveconan.com/file/mangap/5047/10025000/3.jpeg", "https://cdn.readdetectiveconan.com/file/mangap/5047/10025000/4.jpeg", "https://cdn.readdetectiveconan.com/file/mangap/5047/10025000/5.jpeg", "https://cdn.readdetectiveconan.com/file/mangap/5047/10025000/6.jpeg", "https://cdn.readdetectiveconan.com/file/mangap/5047/10025000/7.jpeg", "https://cdn.readdetectiveconan.com/file/mangap/5047/10025000/8.jpeg", "https://cdn.readdetectiveconan.com/file/mangap/5047/10025000/9.jpeg", "https://cdn.readdetectiveconan.com/file/mangap/5047/10025000/10.jpeg", "https://cdn.readdetectiveconan.com/file/mangap/5047/10025000/11.jpeg", "https://cdn.readdetectiveconan.com/file/mangap/5047/10025000/12.jpeg"]}, {"name": "Chapter 20", "order": 20, "panels": ["https://cdn.readdetectiveconan.com/file/mangap/5047/10024000/1.jpeg", "https://cdn.readdetectiveconan.com/file/mangap/5047/10024000/2.jpeg", "https://cdn.readdetectiveconan.com/file/mangap/5047/10024000/3.jpeg", "https://cdn.readdetectiveconan.com/file/mangap/5047/10024000/4.jpeg", "https://cdn.readdetectiveconan.com/file/mangap/5047/10024000/5.jpeg", "https://cdn.readdetectiveconan.com/file/mangap/5047/10024000/6.jpeg", "https://cdn.readdetectiveconan.com/file/mangap/5047/10024000/7.jpeg", "https://cdn.readdetectiveconan.com/file/mangap/5047/10024000/8.jpeg", "https://cdn.readdetectiveconan.com/file/mangap/5047/10024000/9.jpeg", "https://cdn.readdetectiveconan.com/file/mangap/5047/10024000/10.jpeg", "https://cdn.readdetectiveconan.com/file/mangap/5047/10024000/11.jpeg", "https://cdn.readdetectiveconan.com/file/mangap/5047/10024000/12.jpeg"]}, {"name": "Chapter 22", "order": 22, "panels": ["https://cdn.readdetectiveconan.com/file/mangap/5047/10026000/1.jpeg", "https://cdn.readdetectiveconan.com/file/mangap/5047/10026000/2.jpeg", "https://cdn.readdetectiveconan.com/file/mangap/5047/10026000/3.jpeg", "https://cdn.readdetectiveconan.com/file/mangap/5047/10026000/4.jpeg", "https://cdn.readdetectiveconan.com/file/mangap/5047/10026000/5.jpeg", "https://cdn.readdetectiveconan.com/file/mangap/5047/10026000/6.jpeg", "https://cdn.readdetectiveconan.com/file/mangap/5047/10026000/7.jpeg", "https://cdn.readdetectiveconan.com/file/mangap/5047/10026000/8.jpeg", "https://cdn.readdetectiveconan.com/file/mangap/5047/10026000/9.jpeg", "https://cdn.readdetectiveconan.com/file/mangap/5047/10026000/10.jpeg", "https://cdn.readdetectiveconan.com/file/mangap/5047/10026000/11.jpeg", "https://cdn.readdetectiveconan.com/file/mangap/5047/10026000/12.jpeg"]}, {"name": "Chapter 19", "order": 19, "panels": ["https://cdn.readdetectiveconan.com/file/mangap/5047/10023000/1.jpeg", "https://cdn.readdetectiveconan.com/file/mangap/5047/10023000/2.jpeg", "https://cdn.readdetectiveconan.com/file/mangap/5047/10023000/3.jpeg", "https://cdn.readdetectiveconan.com/file/mangap/5047/10023000/4.jpeg", "https://cdn.readdetectiveconan.com/file/mangap/5047/10023000/5.jpeg", "https://cdn.readdetectiveconan.com/file/mangap/5047/10023000/6.jpeg", "https://cdn.readdetectiveconan.com/file/mangap/5047/10023000/7.jpeg", "https://cdn.readdetectiveconan.com/file/mangap/5047/10023000/8.jpeg", "https://cdn.readdetectiveconan.com/file/mangap/5047/10023000/9.jpeg", "https://cdn.readdetectiveconan.com/file/mangap/5047/10023000/10.jpeg", "https://cdn.readdetectiveconan.com/file/mangap/5047/10023000/11.jpeg", "https://cdn.readdetectiveconan.com/file/mangap/5047/10023000/12.jpeg", "https://cdn.readdetectiveconan.com/file/mangap/5047/10023000/13.jpeg"]}, {"name": "Chapter 18", "order": 18, "panels": ["https://cdn.readdetectiveconan.com/file/mangap/5047/10018000/1.jpeg", "https://cdn.readdetectiveconan.com/file/mangap/5047/10018000/2.jpeg", "https://cdn.readdetectiveconan.com/file/mangap/5047/10018000/3.jpeg", "https://cdn.readdetectiveconan.com/file/mangap/5047/10018000/4.jpeg", "https://cdn.readdetectiveconan.com/file/mangap/5047/10018000/5.jpeg", "https://cdn.readdetectiveconan.com/file/mangap/5047/10018000/6.jpeg", "https://cdn.readdetectiveconan.com/file/mangap/5047/10018000/7.jpeg", "https://cdn.readdetectiveconan.com/file/mangap/5047/10018000/8.jpeg", "https://cdn.readdetectiveconan.com/file/mangap/5047/10018000/9.jpeg", "https://cdn.readdetectiveconan.com/file/mangap/5047/10018000/10.jpeg", "https://cdn.readdetectiveconan.com/file/mangap/5047/10018000/11.jpeg", "https://cdn.readdetectiveconan.com/file/mangap/5047/10018000/12.jpeg"]}, {"name": "Chapter 26", "order": 26, "panels": ["https://cdn.readdetectiveconan.com/file/mangap/5047/10029000/1.jpeg", "https://cdn.readdetectiveconan.com/file/mangap/5047/10029000/2.jpeg", "https://cdn.readdetectiveconan.com/file/mangap/5047/10029000/3.jpeg", "https://cdn.readdetectiveconan.com/file/mangap/5047/10029000/4.jpeg", "https://cdn.readdetectiveconan.com/file/mangap/5047/10029000/5.jpeg", "https://cdn.readdetectiveconan.com/file/mangap/5047/10029000/6.jpeg", "https://cdn.readdetectiveconan.com/file/mangap/5047/10029000/7.jpeg", "https://cdn.readdetectiveconan.com/file/mangap/5047/10029000/8.jpeg", "https://cdn.readdetectiveconan.com/file/mangap/5047/10029000/9.jpeg", "https://cdn.readdetectiveconan.com/file/mangap/5047/10029000/10.jpeg", "https://cdn.readdetectiveconan.com/file/mangap/5047/10029000/11.jpeg", "https://cdn.readdetectiveconan.com/file/mangap/5047/10029000/12.jpeg", "https://cdn.readdetectiveconan.com/file/mangap/5047/10029000/13.jpeg", "https://cdn.readdetectiveconan.com/file/mangap/5047/10029000/14.jpeg"]}, {"name": "Chapter 16", "order": 16, "panels": ["https://cdn.readdetectiveconan.com/file/mangap/5047/10016000/1.jpeg", "https://cdn.readdetectiveconan.com/file/mangap/5047/10016000/2.jpeg", "https://cdn.readdetectiveconan.com/file/mangap/5047/10016000/3.jpeg", "https://cdn.readdetectiveconan.com/file/mangap/5047/10016000/4.jpeg", "https://cdn.readdetectiveconan.com/file/mangap/5047/10016000/5.jpeg", "https://cdn.readdetectiveconan.com/file/mangap/5047/10016000/6.jpeg", "https://cdn.readdetectiveconan.com/file/mangap/5047/10016000/7.jpeg", "https://cdn.readdetectiveconan.com/file/mangap/5047/10016000/8.jpeg", "https://cdn.readdetectiveconan.com/file/mangap/5047/10016000/9.jpeg", "https://cdn.readdetectiveconan.com/file/mangap/5047/10016000/10.jpeg", "https://cdn.readdetectiveconan.com/file/mangap/5047/10016000/11.jpeg"]}, {"name": "Chapter 15", "order": 15, "panels": ["https://cdn.readdetectiveconan.com/file/mangap/5047/10015000/1.jpeg", "https://cdn.readdetectiveconan.com/file/mangap/5047/10015000/2.jpeg", "https://cdn.readdetectiveconan.com/file/mangap/5047/10015000/3.jpeg", "https://cdn.readdetectiveconan.com/file/mangap/5047/10015000/4.jpeg", "https://cdn.readdetectiveconan.com/file/mangap/5047/10015000/5.jpeg", "https://cdn.readdetectiveconan.com/file/mangap/5047/10015000/6.jpeg", "https://cdn.readdetectiveconan.com/file/mangap/5047/10015000/7.jpeg", "https://cdn.readdetectiveconan.com/file/mangap/5047/10015000/8.jpeg", "https://cdn.readdetectiveconan.com/file/mangap/5047/10015000/9.jpeg", "https://cdn.readdetectiveconan.com/file/mangap/5047/10015000/10.jpeg", "https://cdn.readdetectiveconan.com/file/mangap/5047/10015000/11.jpeg"]}, {"name": "Chapter 14", "order": 14, "panels": ["https://cdn.readdetectiveconan.com/file/mangap/5047/10014000/1.jpeg", "https://cdn.readdetectiveconan.com/file/mangap/5047/10014000/2.jpeg", "https://cdn.readdetectiveconan.com/file/mangap/5047/10014000/3.jpeg", "https://cdn.readdetectiveconan.com/file/mangap/5047/10014000/4.jpeg", "https://cdn.readdetectiveconan.com/file/mangap/5047/10014000/5.jpeg", "https://cdn.readdetectiveconan.com/file/mangap/5047/10014000/6.jpeg", "https://cdn.readdetectiveconan.com/file/mangap/5047/10014000/7.jpeg", "https://cdn.readdetectiveconan.com/file/mangap/5047/10014000/8.jpeg", "https://cdn.readdetectiveconan.com/file/mangap/5047/10014000/9.jpeg", "https://cdn.readdetectiveconan.com/file/mangap/5047/10014000/10.jpeg", "https://cdn.readdetectiveconan.com/file/mangap/5047/10014000/11.jpeg", "https://cdn.readdetectiveconan.com/file/mangap/5047/10014000/12.jpeg"]}, {"name": "Chapter 23", "order": 23, "panels": ["https://cdn.readdetectiveconan.com/file/mangap/5047/10027000/1.jpeg", "https://cdn.readdetectiveconan.com/file/mangap/5047/10027000/2.jpeg", "https://cdn.readdetectiveconan.com/file/mangap/5047/10027000/3.jpeg", "https://cdn.readdetectiveconan.com/file/mangap/5047/10027000/4.jpeg", "https://cdn.readdetectiveconan.com/file/mangap/5047/10027000/5.jpeg", "https://cdn.readdetectiveconan.com/file/mangap/5047/10027000/6.jpeg", "https://cdn.readdetectiveconan.com/file/mangap/5047/10027000/7.jpeg", "https://cdn.readdetectiveconan.com/file/mangap/5047/10027000/8.jpeg", "https://cdn.readdetectiveconan.com/file/mangap/5047/10027000/9.jpeg", "https://cdn.readdetectiveconan.com/file/mangap/5047/10027000/10.jpeg", "https://cdn.readdetectiveconan.com/file/mangap/5047/10027000/11.jpeg", "https://cdn.readdetectiveconan.com/file/mangap/5047/10027000/12.jpeg"]}, {"name": "Chapter 17", "order": 17, "panels": ["https://cdn.readdetectiveconan.com/file/mangap/5047/10017000/1.jpeg", "https://cdn.readdetectiveconan.com/file/mangap/5047/10017000/2.jpeg", "https://cdn.readdetectiveconan.com/file/mangap/5047/10017000/3.jpeg", "https://cdn.readdetectiveconan.com/file/mangap/5047/10017000/4.jpeg", "https://cdn.readdetectiveconan.com/file/mangap/5047/10017000/5.jpeg", "https://cdn.readdetectiveconan.com/file/mangap/5047/10017000/6.jpeg", "https://cdn.readdetectiveconan.com/file/mangap/5047/10017000/7.jpeg", "https://cdn.readdetectiveconan.com/file/mangap/5047/10017000/8.jpeg", "https://cdn.readdetectiveconan.com/file/mangap/5047/10017000/9.jpeg", "https://cdn.readdetectiveconan.com/file/mangap/5047/10017000/10.jpeg", "https://cdn.readdetectiveconan.com/file/mangap/5047/10017000/11.jpeg", "https://cdn.readdetectiveconan.com/file/mangap/5047/10017000/12.jpeg", "https://cdn.readdetectiveconan.com/file/mangap/5047/10017000/13.jpeg"]}, {"name": "Chapter 13", "order": 13, "panels": ["https://cdn.readdetectiveconan.com/file/mangap/5047/10013000/1.jpg", "https://cdn.readdetectiveconan.com/file/mangap/5047/10013000/2.jpg", "https://cdn.readdetectiveconan.com/file/mangap/5047/10013000/3.jpg", "https://cdn.readdetectiveconan.com/file/mangap/5047/10013000/4.jpg", "https://cdn.readdetectiveconan.com/file/mangap/5047/10013000/5.jpg", "https://cdn.readdetectiveconan.com/file/mangap/5047/10013000/6.jpg", "https://cdn.readdetectiveconan.com/file/mangap/5047/10013000/7.jpg", "https://cdn.readdetectiveconan.com/file/mangap/5047/10013000/8.jpg", "https://cdn.readdetectiveconan.com/file/mangap/5047/10013000/9.jpg", "https://cdn.readdetectiveconan.com/file/mangap/5047/10013000/10.jpg", "https://cdn.readdetectiveconan.com/file/mangap/5047/10013000/11.jpg"]}, {"name": "Chapter 10", "order": 10, "panels": ["https://cdn.readdetectiveconan.com/file/mangap/5047/10010000/1.jpeg", "https://cdn.readdetectiveconan.com/file/mangap/5047/10010000/2.jpeg", "https://cdn.readdetectiveconan.com/file/mangap/5047/10010000/3.jpeg", "https://cdn.readdetectiveconan.com/file/mangap/5047/10010000/4.jpeg", "https://cdn.readdetectiveconan.com/file/mangap/5047/10010000/5.jpeg", "https://cdn.readdetectiveconan.com/file/mangap/5047/10010000/6.jpeg", "https://cdn.readdetectiveconan.com/file/mangap/5047/10010000/7.jpeg", "https://cdn.readdetectiveconan.com/file/mangap/5047/10010000/8.jpeg", "https://cdn.readdetectiveconan.com/file/mangap/5047/10010000/9.jpeg", "https://cdn.readdetectiveconan.com/file/mangap/5047/10010000/10.jpeg", "https://cdn.readdetectiveconan.com/file/mangap/5047/10010000/11.jpeg"]}, {"name": "Chapter 12", "order": 12, "panels": ["https://cdn.readdetectiveconan.com/file/mangap/5047/10012000/1.jpg", "https://cdn.readdetectiveconan.com/file/mangap/5047/10012000/2.jpg", "https://cdn.readdetectiveconan.com/file/mangap/5047/10012000/3.jpg", "https://cdn.readdetectiveconan.com/file/mangap/5047/10012000/4.jpg", "https://cdn.readdetectiveconan.com/file/mangap/5047/10012000/5.jpg", "https://cdn.readdetectiveconan.com/file/mangap/5047/10012000/6.jpg", "https://cdn.readdetectiveconan.com/file/mangap/5047/10012000/7.jpg", "https://cdn.readdetectiveconan.com/file/mangap/5047/10012000/8.jpg", "https://cdn.readdetectiveconan.com/file/mangap/5047/10012000/9.jpg", "https://cdn.readdetectiveconan.com/file/mangap/5047/10012000/10.jpg", "https://cdn.readdetectiveconan.com/file/mangap/5047/10012000/11.jpg"]}, {"name": "Chapter 9", "order": 9, "panels": ["https://cdn.readdetectiveconan.com/file/mangap/5047/10009000/1.jpeg", "https://cdn.readdetectiveconan.com/file/mangap/5047/10009000/2.jpeg", "https://cdn.readdetectiveconan.com/file/mangap/5047/10009000/3.jpeg", "https://cdn.readdetectiveconan.com/file/mangap/5047/10009000/4.jpeg", "https://cdn.readdetectiveconan.com/file/mangap/5047/10009000/5.jpeg", "https://cdn.readdetectiveconan.com/file/mangap/5047/10009000/6.jpeg", "https://cdn.readdetectiveconan.com/file/mangap/5047/10009000/7.jpeg", "https://cdn.readdetectiveconan.com/file/mangap/5047/10009000/8.jpeg", "https://cdn.readdetectiveconan.com/file/mangap/5047/10009000/9.jpeg", "https://cdn.readdetectiveconan.com/file/mangap/5047/10009000/10.jpeg", "https://cdn.readdetectiveconan.com/file/mangap/5047/10009000/11.jpeg"]}, {"name": "Chapter 8", "order": 8, "panels": ["https://cdn.readdetectiveconan.com/file/mangap/5047/10008000/1.jpeg", "https://cdn.readdetectiveconan.com/file/mangap/5047/10008000/2.jpeg", "https://cdn.readdetectiveconan.com/file/mangap/5047/10008000/3.jpeg", "https://cdn.readdetectiveconan.com/file/mangap/5047/10008000/4.jpeg", "https://cdn.readdetectiveconan.com/file/mangap/5047/10008000/5.jpeg", "https://cdn.readdetectiveconan.com/file/mangap/5047/10008000/6.jpeg", "https://cdn.readdetectiveconan.com/file/mangap/5047/10008000/7.jpeg", "https://cdn.readdetectiveconan.com/file/mangap/5047/10008000/8.jpeg", "https://cdn.readdetectiveconan.com/file/mangap/5047/10008000/9.jpeg", "https://cdn.readdetectiveconan.com/file/mangap/5047/10008000/10.jpeg", "https://cdn.readdetectiveconan.com/file/mangap/5047/10008000/11.jpeg"]}, {"name": "Chapter 7", "order": 7, "panels": ["https://cdn.readdetectiveconan.com/file/mangap/5047/10007000/1.jpeg", "https://cdn.readdetectiveconan.com/file/mangap/5047/10007000/2.jpeg", "https://cdn.readdetectiveconan.com/file/mangap/5047/10007000/3.jpeg", "https://cdn.readdetectiveconan.com/file/mangap/5047/10007000/4.jpeg", "https://cdn.readdetectiveconan.com/file/mangap/5047/10007000/5.jpeg", "https://cdn.readdetectiveconan.com/file/mangap/5047/10007000/6.jpeg", "https://cdn.readdetectiveconan.com/file/mangap/5047/10007000/7.jpeg", "https://cdn.readdetectiveconan.com/file/mangap/5047/10007000/8.jpeg", "https://cdn.readdetectiveconan.com/file/mangap/5047/10007000/9.jpeg", "https://cdn.readdetectiveconan.com/file/mangap/5047/10007000/10.jpeg", "https://cdn.readdetectiveconan.com/file/mangap/5047/10007000/11.jpeg", "https://cdn.readdetectiveconan.com/file/mangap/5047/10007000/12.jpeg"]}, {"name": "Chapter 6", "order": 6, "panels": ["https://cdn.readdetectiveconan.com/file/mangap/5047/10006000/1.jpeg", "https://cdn.readdetectiveconan.com/file/mangap/5047/10006000/2.jpeg", "https://cdn.readdetectiveconan.com/file/mangap/5047/10006000/3.jpeg", "https://cdn.readdetectiveconan.com/file/mangap/5047/10006000/4.jpeg", "https://cdn.readdetectiveconan.com/file/mangap/5047/10006000/5.jpeg", "https://cdn.readdetectiveconan.com/file/mangap/5047/10006000/6.jpeg", "https://cdn.readdetectiveconan.com/file/mangap/5047/10006000/7.jpeg", "https://cdn.readdetectiveconan.com/file/mangap/5047/10006000/8.jpeg", "https://cdn.readdetectiveconan.com/file/mangap/5047/10006000/9.jpeg"]}, {"name": "Chapter 3", "order": 3, "panels": ["https://cdn.readdetectiveconan.com/file/mangap/5047/10003000/1.jpeg", "https://cdn.readdetectiveconan.com/file/mangap/5047/10003000/2.jpeg", "https://cdn.readdetectiveconan.com/file/mangap/5047/10003000/3.jpeg", "https://cdn.readdetectiveconan.com/file/mangap/5047/10003000/4.jpeg", "https://cdn.readdetectiveconan.com/file/mangap/5047/10003000/5.jpeg", "https://cdn.readdetectiveconan.com/file/mangap/5047/10003000/6.jpeg", "https://cdn.readdetectiveconan.com/file/mangap/5047/10003000/7.jpeg", "https://cdn.readdetectiveconan.com/file/mangap/5047/10003000/8.jpeg", "https://cdn.readdetectiveconan.com/file/mangap/5047/10003000/9.jpeg", "https://cdn.readdetectiveconan.com/file/mangap/5047/10003000/10.jpeg", "https://cdn.readdetectiveconan.com/file/mangap/5047/10003000/11.jpeg"]}, {"name": "Chapter 4", "order": 4, "panels": ["https://cdn.readdetectiveconan.com/file/mangap/5047/10004000/1.jpeg", "https://cdn.readdetectiveconan.com/file/mangap/5047/10004000/2.jpeg", "https://cdn.readdetectiveconan.com/file/mangap/5047/10004000/3.jpeg", "https://cdn.readdetectiveconan.com/file/mangap/5047/10004000/4.jpeg", "https://cdn.readdetectiveconan.com/file/mangap/5047/10004000/5.jpeg", "https://cdn.readdetectiveconan.com/file/mangap/5047/10004000/6.jpeg", "https://cdn.readdetectiveconan.com/file/mangap/5047/10004000/7.jpeg", "https://cdn.readdetectiveconan.com/file/mangap/5047/10004000/8.jpeg", "https://cdn.readdetectiveconan.com/file/mangap/5047/10004000/9.jpeg", "https://cdn.readdetectiveconan.com/file/mangap/5047/10004000/10.jpeg", "https://cdn.readdetectiveconan.com/file/mangap/5047/10004000/11.jpeg"]}, {"name": "Chapter 2", "order": 2, "panels": ["https://cdn.readdetectiveconan.com/file/mangap/5047/10002000/1.jpeg", "https://cdn.readdetectiveconan.com/file/mangap/5047/10002000/2.jpeg", "https://cdn.readdetectiveconan.com/file/mangap/5047/10002000/3.jpeg", "https://cdn.readdetectiveconan.com/file/mangap/5047/10002000/4.jpeg", "https://cdn.readdetectiveconan.com/file/mangap/5047/10002000/5.jpeg", "https://cdn.readdetectiveconan.com/file/mangap/5047/10002000/6.jpeg", "https://cdn.readdetectiveconan.com/file/mangap/5047/10002000/7.jpeg", "https://cdn.readdetectiveconan.com/file/mangap/5047/10002000/8.jpeg", "https://cdn.readdetectiveconan.com/file/mangap/5047/10002000/9.jpeg", "https://cdn.readdetectiveconan.com/file/mangap/5047/10002000/10.jpeg", "https://cdn.readdetectiveconan.com/file/mangap/5047/10002000/11.jpeg"]}, {"name": "Chapter 11", "order": 11, "panels": ["https://cdn.readdetectiveconan.com/file/mangap/5047/10011000/1.jpeg", "https://cdn.readdetectiveconan.com/file/mangap/5047/10011000/2.jpeg", "https://cdn.readdetectiveconan.com/file/mangap/5047/10011000/3.jpeg", "https://cdn.readdetectiveconan.com/file/mangap/5047/10011000/4.jpeg", "https://cdn.readdetectiveconan.com/file/mangap/5047/10011000/5.jpeg", "https://cdn.readdetectiveconan.com/file/mangap/5047/10011000/6.jpeg", "https://cdn.readdetectiveconan.com/file/mangap/5047/10011000/7.jpeg", "https://cdn.readdetectiveconan.com/file/mangap/5047/10011000/8.jpeg", "https://cdn.readdetectiveconan.com/file/mangap/5047/10011000/9.jpeg", "https://cdn.readdetectiveconan.com/file/mangap/5047/10011000/10.jpeg", "https://cdn.readdetectiveconan.com/file/mangap/5047/10011000/11.jpeg", "https://cdn.readdetectiveconan.com/file/mangap/5047/10011000/12.jpeg"]}, {"name": "Chapter 0", "order": 0, "panels": ["https://cdn.readdetectiveconan.com/file/mangap/5047/10000000/1.jpeg", "https://cdn.readdetectiveconan.com/file/mangap/5047/10000000/2.jpeg", "https://cdn.readdetectiveconan.com/file/mangap/5047/10000000/3.jpeg", "https://cdn.readdetectiveconan.com/file/mangap/5047/10000000/4.jpeg"]}, {"name": "Chapter 5", "order": 5, "panels": ["https://cdn.readdetectiveconan.com/file/mangap/5047/10005000/1.jpeg", "https://cdn.readdetectiveconan.com/file/mangap/5047/10005000/2.jpeg", "https://cdn.readdetectiveconan.com/file/mangap/5047/10005000/3.jpeg", "https://cdn.readdetectiveconan.com/file/mangap/5047/10005000/4.jpeg", "https://cdn.readdetectiveconan.com/file/mangap/5047/10005000/5.jpeg", "https://cdn.readdetectiveconan.com/file/mangap/5047/10005000/6.jpeg", "https://cdn.readdetectiveconan.com/file/mangap/5047/10005000/7.jpeg", "https://cdn.readdetectiveconan.com/file/mangap/5047/10005000/8.jpeg", "https://cdn.readdetectiveconan.com/file/mangap/5047/10005000/9.jpeg", "https://cdn.readdetectiveconan.com/file/mangap/5047/10005000/10.jpeg", "https://cdn.readdetectiveconan.com/file/mangap/5047/10005000/11.jpeg", "https://cdn.readdetectiveconan.com/file/mangap/5047/10005000/12.jpeg", "https://cdn.readdetectiveconan.com/file/mangap/5047/10005000/13.jpeg", "https://cdn.readdetectiveconan.com/file/mangap/5047/10005000/14.jpeg", "https://cdn.readdetectiveconan.com/file/mangap/5047/10005000/15.jpeg"]}, {"name": "Chapter 1", "order": 1, "panels": ["https://cdn.readdetectiveconan.com/file/mangap/5047/10001000/1.jpeg", "https://cdn.readdetectiveconan.com/file/mangap/5047/10001000/2.jpeg", "https://cdn.readdetectiveconan.com/file/mangap/5047/10001000/3.jpeg", "https://cdn.readdetectiveconan.com/file/mangap/5047/10001000/4.jpeg", "https://cdn.readdetectiveconan.com/file/mangap/5047/10001000/5.jpeg", "https://cdn.readdetectiveconan.com/file/mangap/5047/10001000/6.jpeg", "https://cdn.readdetectiveconan.com/file/mangap/5047/10001000/7.jpeg", "https://cdn.readdetectiveconan.com/file/mangap/5047/10001000/8.jpeg", "https://cdn.readdetectiveconan.com/file/mangap/5047/10001000/9.jpeg", "https://cdn.readdetectiveconan.com/file/mangap/5047/10001000/10.jpeg", "https://cdn.readdetectiveconan.com/file/mangap/5047/10001000/11.jpeg", "https://cdn.readdetectiveconan.com/file/mangap/5047/10001000/12.jpeg", "https://cdn.readdetectiveconan.com/file/mangap/5047/10001000/13.jpeg", "https://cdn.readdetectiveconan.com/file/mangap/5047/10001000/14.jpeg", "https://cdn.readdetectiveconan.com/file/mangap/5047/10001000/15.jpeg", "https://cdn.readdetectiveconan.com/file/mangap/5047/10001000/16.jpeg", "https://cdn.readdetectiveconan.com/file/mangap/5047/10001000/17.jpeg", "https://cdn.readdetectiveconan.com/file/mangap/5047/10001000/18.jpeg", "https://cdn.readdetectiveconan.com/file/mangap/5047/10001000/19.jpeg", "https://cdn.readdetectiveconan.com/file/mangap/5047/10001000/20.jpeg", "https://cdn.readdetectiveconan.com/file/mangap/5047/10001000/21.jpeg"]}], "chapter_links": ["https://mangapill.com/chapters/5047-10000000/reiwa-hanamaru-gakuen-chapter-0", "https://mangapill.com/chapters/5047-10001000/reiwa-hanamaru-gakuen-chapter-1", "https://mangapill.com/chapters/5047-10002000/reiwa-hanamaru-gakuen-chapter-2", "https://mangapill.com/chapters/5047-10003000/reiwa-hanamaru-gakuen-chapter-3", "https://mangapill.com/chapters/5047-10004000/reiwa-hanamaru-gakuen-chapter-4", "https://mangapill.com/chapters/5047-10005000/reiwa-hanamaru-gakuen-chapter-5", "https://mangapill.com/chapters/5047-10006000/reiwa-hanamaru-gakuen-chapter-6", "https://mangapill.com/chapters/5047-10007000/reiwa-hanamaru-gakuen-chapter-7", "https://mangapill.com/chapters/5047-10008000/reiwa-hanamaru-gakuen-chapter-8", "https://mangapill.com/chapters/5047-10009000/reiwa-hanamaru-gakuen-chapter-9", "https://mangapill.com/chapters/5047-10010000/reiwa-hanamaru-gakuen-chapter-10", "https://mangapill.com/chapters/5047-10011000/reiwa-hanamaru-gakuen-chapter-11", "https://mangapill.com/chapters/5047-10012000/reiwa-hanamaru-gakuen-chapter-12", "https://mangapill.com/chapters/5047-10013000/reiwa-hanamaru-gakuen-chapter-13", "https://mangapill.com/chapters/5047-10014000/reiwa-hanamaru-gakuen-chapter-14", "https://mangapill.com/chapters/5047-10015000/reiwa-hanamaru-gakuen-chapter-15", "https://mangapill.com/chapters/5047-10016000/reiwa-hanamaru-gakuen-chapter-16", "https://mangapill.com/chapters/5047-10017000/reiwa-hanamaru-gakuen-chapter-17", "https://mangapill.com/chapters/5047-10018000/reiwa-hanamaru-gakuen-chapter-18", "https://mangapill.com/chapters/5047-10023000/reiwa-hanamaru-gakuen-chapter-23", "https://mangapill.com/chapters/5047-10024000/reiwa-hanamaru-gakuen-chapter-24", "https://mangapill.com/chapters/5047-10025000/reiwa-hanamaru-gakuen-chapter-25", "https://mangapill.com/chapters/5047-10026000/reiwa-hanamaru-gakuen-chapter-26", "https://mangapill.com/chapters/5047-10027000/reiwa-hanamaru-gakuen-chapter-27", "https://mangapill.com/chapters/5047-10027500/reiwa-hanamaru-gakuen-chapter-27.5", "https://mangapill.com/chapters/5047-10028000/reiwa-hanamaru-gakuen-chapter-28", "https://mangapill.com/chapters/5047-10029000/reiwa-hanamaru-gakuen-chapter-29", "https://mangapill.com/chapters/5047-10030000/reiwa-hanamaru-gakuen-chapter-30", "https://mangapill.com/chapters/5047-10031000/reiwa-hanamaru-gakuen-chapter-31", "https://mangapill.com/chapters/5047-10032000/reiwa-hanamaru-gakuen-chapter-32"]}